switrs_to_sqlite/__init__.py
switrs_to_sqlite/converters.py
switrs_to_sqlite/datatypes.py
switrs_to_sqlite/main.py
switrs_to_sqlite/make_map.py
switrs_to_sqlite/open_record.py
switrs_to_sqlite/parsers.py
switrs_to_sqlite/row_types.py
switrs_to_sqlite/schema.py
switrs_to_sqlite/value_maps.py
switrs_to_sqlite-4.5.0.dist-info/METADATA
switrs_to_sqlite-4.5.0.dist-info/WHEEL
switrs_to_sqlite-4.5.0.dist-info/entry_points.txt
switrs_to_sqlite-4.5.0.dist-info/licenses/LICENSE.md
switrs_to_sqlite-4.5.0.dist-info/RECORD
