Metadata-Version: 2.4
Name: switrs-to-sqlite
Version: 4.5.0
Summary: Script for converting SWITRS reports to SQLite.
Project-URL: Homepage, https://github.com/agude/SWITRS-to-SQLite
Project-URL: Repository, https://github.com/agude/SWITRS-to-SQLite
Author-email: Alexander Gude <alex.public.account@gmail.com>
License-Expression: GPL-3.0-or-later
License-File: LICENSE.md
Keywords: data,sqlite,switrs
Classifier: Development Status :: 5 - Production/Stable
Classifier: Environment :: Console
Classifier: Intended Audience :: Science/Research
Classifier: License :: OSI Approved :: GNU General Public License v3 or later (GPLv3+)
Classifier: Natural Language :: English
Classifier: Operating System :: OS Independent
Classifier: Programming Language :: Python :: 3
Classifier: Programming Language :: Python :: 3.10
Classifier: Programming Language :: Python :: 3.11
Classifier: Programming Language :: Python :: 3.12
Classifier: Programming Language :: Python :: 3.13
Classifier: Programming Language :: Python :: 3.14
Classifier: Topic :: Utilities
Requires-Python: >=3.10
